pdf_zipper/__init__.py
pdf_zipper/cli.py
pdf_zipper/core.py
pdf_zipper/gui.py
pdf_zipper-1.2.2.dist-info/METADATA
pdf_zipper-1.2.2.dist-info/WHEEL
pdf_zipper-1.2.2.dist-info/entry_points.txt
pdf_zipper-1.2.2.dist-info/licenses/LICENSE
pdf_zipper-1.2.2.dist-info/RECORD
