Metadata-Version: 2.4
Name: pdf-zipper
Version: 1.2.2
Summary: A powerful file processing tool supporting PDF compression and PDF/PPTX conversion with GUI and CLI interfaces
Project-URL: Homepage, https://github.com/wibus-wee/pdf-zipper
Project-URL: Repository, https://github.com/wibus-wee/pdf-zipper
Project-URL: Issues, https://github.com/wibus-wee/pdf-zipper/issues
Author-email: PDF Zipper Team <team@pdfzipper.com>
License-Expression: MIT
License-File: LICENSE
Keywords: cli,compression,conversion,gui,pdf,powerpoint,pptx,textual
Classifier: Development Status :: 4 - Beta
Classifier: Environment :: Console
Classifier: Environment :: Console :: Curses
Classifier: Intended Audience :: End Users/Desktop
Classifier: License :: OSI Approved :: MIT License
Classifier: Operating System :: OS Independent
Classifier: Programming Language :: Python :: 3
Classifier: Programming Language :: Python :: 3.8
Classifier: Programming Language :: Python :: 3.9
Classifier: Programming Language :: Python :: 3.10
Classifier: Programming Language :: Python :: 3.11
Classifier: Programming Language :: Python :: 3.12
Classifier: Programming Language :: Python :: 3.13
Classifier: Topic :: Multimedia :: Graphics
Classifier: Topic :: Office/Business
Classifier: Topic :: Utilities
Requires-Python: >=3.8
Requires-Dist: click>=8.0.0
Requires-Dist: comtypes>=1.1.14; sys_platform == 'win32'
Requires-Dist: pillow>=10.0.0
Requires-Dist: pymupdf>=1.23.0
Requires-Dist: python-pptx>=0.6.21
Requires-Dist: pywin32>=306; sys_platform == 'win32'
Requires-Dist: rich>=13.0.0
Requires-Dist: textual>=0.31.0
Requires-Dist: typer>=0.9.0
Provides-Extra: build
Requires-Dist: build>=1.0.0; extra == 'build'
Requires-Dist: pyinstaller>=6.0.0; extra == 'build'
Requires-Dist: twine>=4.0.0; extra == 'build'
Provides-Extra: dev
Requires-Dist: black>=23.0.0; extra == 'dev'
Requires-Dist: flake8>=6.0.0; extra == 'dev'
Requires-Dist: isort>=5.12.0; extra == 'dev'
Requires-Dist: mypy>=1.0.0; extra == 'dev'
Requires-Dist: pytest-cov>=4.0.0; extra == 'dev'
Requires-Dist: pytest>=7.0.0; extra == 'dev'
